operator_sdk_manager/__about__.py
operator_sdk_manager/__init__.py
operator_sdk_manager/main.py
operator_sdk_manager/update.py
operator_sdk_manager/util.py
operator_sdk_manager-0.1.10.dist-info/LICENSE
operator_sdk_manager-0.1.10.dist-info/METADATA
operator_sdk_manager-0.1.10.dist-info/WHEEL
operator_sdk_manager-0.1.10.dist-info/entry_points.txt
operator_sdk_manager-0.1.10.dist-info/top_level.txt
operator_sdk_manager-0.1.10.dist-info/RECORD
